{"id":"index.html","dependencies":[{"name":"D:\\web\\workspace\\react\\diff\\package.json","includedInParent":true,"mtime":1533282601523},{"name":"./src\\index.js","dynamic":true,"parent":"D:\\web\\workspace\\react\\diff\\index.html","resolved":"D:\\web\\workspace\\react\\diff\\src\\index.js"}],"generated":{"html":"<!DOCTYPE html>\r\n<html lang=\"en\">\r\n<head>\r\n  <meta charset=\"UTF-8\">\r\n  <meta name=\"viewport\" content=\"width=device-width, initial-scale=1.0\">\r\n  <meta http-equiv=\"X-UA-Compatible\" content=\"ie=edge\">\r\n  <title>Document</title>\r\n  <style>\r\n  .rt{\r\n    color: red;\r\n  }\r\n  </style>\r\n</head>\r\n<body>\r\n  <div id=\"root\"></div>\r\n  <script src=\"/8902dccdc2f0884373c999cc4c781b36.js\"></script>\r\n</body>\r\n</html>"},"hash":"e302d6bcfd50d72506f17d37160197d5","cacheData":{}}